Workbook

Sheet Vol Surface
A5: Volatility Surface Input · August 2026
A6: Implied volatility in percent points by strike and expiry. Strike rows are live formulas of the reference prices times the Strike Change.
A7: Anand Rathi Wealth · Hedging Sheet
A9: Strike Change | B9: Deep | C9: 0.55 | D9: 0.6 | E9: 0.65 | F9: 0.7 | G9: 0.75 | H9: 0.8 | I9: 0.85 | J9: 0.9 | K9: 0.95 | L9: 1 | M9: 1.05 | N9: 1.1 | O9: 1.15 | P9: 1.2 | Q9: 1.25 | R9: 1.3 | S9: 1.35 | T9: 1.4 | U9: 1.45 | V9: 1.5
A10: Nifty Strikes | B10: 500 | C10: ='Surface Parameters'!$B$11*C9 -> 13197.773 | D10: ='Surface Parameters'!$B$11*D9 -> 14397.57 | E10: ='Surface Parameters'!$B$11*E9 -> 15597.368 | F10: ='Surface Parameters'!$B$11*F9 -> 16797.165 | G10: ='Surface Parameters'!$B$11*G9 -> 17996.963 | H10: ='Surface Parameters'!$B$11*H9 -> 19196.76 | I10: ='Surface Parameters'!$B$11*I9 -> 20396.557 | J10: ='Surface Parameters'!$B$11*J9 -> 21596.355 | ... V10: ='Surface Parameters'!$B$11*V9 -> 35993.925
A11: Sensex Strikes | B11: 500 | C11: ='Surface Parameters'!$B$12*C9 -> 42259.679 | D11: ='Surface Parameters'!$B$12*D9 -> 46101.468 | E11: ='Surface Parameters'!$B$12*E9 -> 49943.257 | F11: ='Surface Parameters'!$B$12*F9 -> 53785.046 | G11: ='Surface Parameters'!$B$12*G9 -> 57626.835 | H11: ='Surface Parameters'!$B$12*H9 -> 61468.624 | I11: ='Surface Parameters'!$B$12*I9 -> 65310.413 | J11: ='Surface Parameters'!$B$12*J9 -> 69152.202 | ... V11: ='Surface Parameters'!$B$12*V9 -> 115253.67
A12: Expiry Date
A13: 46203 | B13: 50.9 | C13: 53.5 | D13: 47.64 | E13: 42.07 | F13: 37.05 | G13: 32.77 | H13: 35.16 | I13: 28.86 | J13: 22.55 | K13: 16.8 | L13: 13.51 | M13: 14.32 | N13: 17.91 | O13: 21.78 | P13: 26.23 | Q13: 22.4 | R13: 24.56 | S13: 26.53 | T13: 32.17 | U13: 34.35 | V13: 36.37
A14: 46231 | B14: 50.9 | C14: 46.24 | D14: 42.14 | E14: 38.09 | F14: 33.95 | G14: 29.84 | H14: 25.96 | I14: 22.07 | J14: 18.57 | K14: 15.8 | L14: 13.88 | M14: 12.96 | N14: 13.73 | O14: 15.59 | P14: 17.81 | Q14: 19.27 | R14: 20.93 | S14: 22.55 | T14: 24.05 | U14: 25.62 | V14: 27.59
A15: 46259 | B15: 45.12 | C15: 46.12 | D15: 42.11 | E15: 37.78 | F15: 33.33 | G15: 29.25 | H15: 25.42 | I15: 21.36 | J15: 17.56 | K15: 14.39 | L15: 12.45 | M15: 11.42 | N15: 12.28 | O15: 14.03 | P15: 16.17 | Q15: 17.89 | R15: 19.57 | S15: 21.18 | T15: 23.54 | U15: 25.69 | V15: 27.39
A16: 46294 | B16: 41.94 | C16: 38.38 | D16: 35.2 | E16: 32.01 | F16: 28.81 | G16: 25.62 | H16: 22.51 | I16: 19.37 | J16: 16.46 | K16: 14.27 | L16: 12.85 | M16: 11.76 | N16: 11.7 | O16: 12.79 | P16: 14.18 | Q16: 15.82 | R16: 17.25 | S16: 18.59 | T16: 19.84 | U16: 21.02 | V16: 22.13
A17: 46322 | B17: 35.68 | C17: 37.26 | D17: 34.04 | E17: 30.84 | F17: 27.68 | G17: 24.56 | H17: 21.63 | I17: 18.78 | J17: 16.14 | K17: 14.17 | L17: 12.84 | M17: 11.82 | N17: 11.66 | O17: 12.5 | P17: 13.83 | Q17: 15.48 | R17: 16.9 | S17: 18.27 | T17: 19.57 | U17: 20.82 | V17: 22.01
A18: 46385 | B18: 35.68 | C18: 33.39 | D18: 30.67 | E18: 27.97 | F18: 25.31 | G18: 22.74 | H18: 20.29 | I18: 17.95 | J18: 15.91 | K18: 14.32 | L18: 13.14 | M18: 12.16 | N18: 11.56 | O18: 11.62 | P18: 12.26 | Q18: 13.16 | R18: 14.1 | S18: 15.03 | T18: 15.94 | U18: 16.82 | V18: 17.66
A19: 46476 | B19: 31.5 | C19: 30.78 | D19: 28.4 | E19: 26.09 | F19: 23.85 | G19: 21.73 | H19: 19.7 | I19: 17.86 | J19: 16.25 | K19: 14.92 | L19: 13.79 | M19: 12.87 | N19: 12.2 | O19: 11.85 | P19: 11.92 | Q19: 12.33 | R19: 12.91 | S19: 13.59 | T19: 14.3 | U19: 15.02 | V19: 15.74
A20: 46567 | B20: 29.84 | C20: 28.9 | D20: 26.84 | E20: 24.85 | F20: 22.94 | G20: 21.12 | H20: 19.39 | I20: 17.81 | J20: 16.37 | K20: 15.16 | L20: 14.14 | M20: 13.28 | N20: 12.61 | O20: 12.15 | P20: 11.96 | Q20: 12.09 | R20: 12.4 | S20: 12.77 | T20: 13.22 | U20: 13.71 | V20: 14.22
A21: 46658 | B21: 28.45 | C21: 28.22 | D21: 26.25 | E21: 24.39 | F21: 22.67 | G21: 21.05 | H21: 19.52 | I21: 18.1 | J21: 16.81 | K21: 15.7 | L21: 14.73 | M21: 13.91 | N21: 13.26 | O21: 12.8 | P21: 12.51 | Q21: 12.41 | R21: 12.54 | S21: 12.78 | T21: 13.07 | U21: 13.4 | V21: 13.77
A22: 46749 | B22: 27.36 | C22: 27.57 | D22: 25.75 | E22: 24.06 | F22: 22.48 | G22: 21.01 | H22: 19.63 | I22: 18.33 | J22: 17.15 | K22: 16.09 | L22: 15.17 | M22: 14.37 | N22: 13.72 | O22: 13.22 | P22: 12.88 | Q22: 12.68 | R22: 12.64 | S22: 12.73 | T22: 12.91 | U22: 13.18 | V22: 13.51
A23: 46840 | B23: 26.78 | C23: 26.95 | D23: 25.27 | E23: 23.71 | F23: 22.27 | G23: 20.95 | H23: 19.71 | I23: 18.54 | J23: 17.45 | K23: 16.46 | L23: 15.58 | M23: 14.81 | N23: 14.15 | O23: 13.63 | P23: 13.25 | Q23: 12.99 | R23: 12.83 | S23: 12.76 | T23: 12.84 | U23: 13.01 | V23: 13.26
A24: 46931 | B24: 26.16 | C24: 26.49 | D24: 24.94 | E24: 23.5 | F24: 22.17 | G24: 20.96 | H24: 19.81 | I24: 18.7 | J24: 17.67 | K24: 16.72 | L24: 15.87 | M24: 15.13 | N24: 14.48 | O24: 13.95 | P24: 13.54 | Q24: 13.25 | R24: 13.06 | S24: 12.91 | T24: 12.87 | U24: 12.94 | V24: 13.11
... A30: 47962 | B30: 28.46 | C30: 25.74 | D30: 24.69 | E30: 23.68 | F30: 22.71 | G30: 21.78 | H30: 20.88 | I30: 20.02 | J30: 19.2 | K30: 18.42 | L30: 17.69 | M30: 17.02 | N30: 16.41 | O30: 15.85 | P30: 15.35 | Q30: 14.92 | R30: 14.55 | S30: 14.26 | T30: 13.99 | U30: 13.79 | V30: 13.65

Sheet Surface Parameters
A5: Surface Parameters · August 2026
A6: Reference prices are the 100 percent anchors of the Strike Change columns. The Pricing Params table is read by expiry date.
A7: Anand Rathi Wealth · Hedging Sheet
A9: Parameter | B9: Value
A10: Month | B10: August 2026
A11: Reference Nifty Price | B11: 23995.95
A12: Reference Sensex Price | B12: 76835.78
A13: Volatility Bump | B13: 0
A14: Forward Sell Rate | B14: 0.055
A15: Rate Cap While Buying Forward | B15: 0.068
A16: Dividend Bid Offer Multiplier | B16: 1
A19: Date | B19: BID | C19: Inc. Margin | D19: Full Margin | E19: Margin Cost | F19: Fwd Sell rate
A20: 43916 | B20: 0 | C20: 0.005 | D20: 0.065 | E20: 0.03 | F20: 0
A21: 44007 | B21: 0 | C21: 0.005 | D21: 0.065 | E21: 0.03 | F21: 0
A22: 44042 | B22: 0 | C22: 0.005 | D22: 0.065 | E22: 0.03 | F22: 0
A23: 44070 | B23: 0 | C23: 0.005 | D23: 0.065 | E23: 0.03 | F23: 0.001
A24: 44098 | B24: 0 | C24: 0.005 | D24: 0.065 | E24: 0.03 | F24: 0.001
A25: 44133 | B25: 0 | C25: 0.005 | D25: 0.065 | E25: 0.03 | F25: 0.006
A26: 44160 | B26: 0 | C26: 0.005 | D26: 0.065 | E26: 0.03 | F26: 0.006
A27: 44196 | B27: 0 | C27: 0.005 | D27: 0.065 | E27: 0.03 | F27: 0.0085
A28: 44224 | B28: 0 | C28: 0.005 | D28: 0.065 | E28: 0.03 | F28: 0.0085
A29: 44252 | B29: 0 | C29: 0.005 | D29: 0.065 | E29: 0.03 | F29: 0.0085
A30: 44280 | B30: 0 | C30: 0.005 | D30: 0.065 | E30: 0.03 | F30: 0.031
A31: 44315 | B31: 0 | C31: 0.011930693 | D31: 0.071930693 | E31: 0.03 | F31: 0.031
... A142: 47962 | B142: 0 | C142: 0.060285605 | D142: 0.12028561 | E142: 0.03 | F142: 0.055

Sheet Rate Curve
A5: Rate Curve
A6: Discount curve points in percent per annum. Leave the last points at the Premium Growth Rate to match the workbook.
A7: Anand Rathi Wealth · Hedging Sheet
A9: Date | B9: Rate In Percent
A10: 44196 | B10: 4.1983864
A11: 44280 | B11: 4.2599787
A12: 44371 | B12: 4.5
A13: 44560 | B13: 4.5
A14: 44742 | B14: 4.58
A15: 44924 | B15: 4.58
A16: 45105 | B16: 6.5
A17: 45288 | B17: 6.5
A18: 46021 | B18: 6.5

Sheet Dividends
A5: Implied Dividends
A6: Monthly implied dividends in Sensex index points.
A7: Anand Rathi Wealth · Hedging Sheet
A9: Date | B9: Implied Dividend
A10: 43739 | B10: 0.263
A11: 43770 | B11: 0
A12: 43800 | B12: 0.493
A13: 43831 | B13: 3.305
A14: 43862 | B14: 16.809
A15: 43891 | B15: 17.337
A16: 43922 | B16: 0
A17: 43952 | B17: 1.592
A18: 43983 | B18: 46.679
A19: 44013 | B19: 42.171
A20: 44044 | B20: 13.681
A21: 44075 | B21: 3.689
... A128: 47329 | B128: 18.691
